README.md
setup.py
photoutils/__init__.py
photoutils/cvzone_rembg.py
photoutils/image_cartoon.py
photoutils/image_text.py
photoutils/imagevideo.py
photoutils/kivytexture.py
photoutils/mediapipe_remove.py
photoutils/np_geometric.py
photoutils/np_image.py
photoutils/rembg_remove.py
photoutils/t.py
photoutils/test.py
photoutils/test_text.py
photoutils/to_video.py
photoutils/version.py
photoutils.egg-info/PKG-INFO
photoutils.egg-info/SOURCES.txt
photoutils.egg-info/dependency_links.txt
photoutils.egg-info/top_level.txt