Metadata-Version: 2.1
Name: photoutils
Version: 0.0.1
Summary: photoutils is contains a set of photo utilitiesi and function
Author: yumoqing
Author-email: yumoqing@icloud.com
Platform: any
Classifier: Development Status :: 3 - Alpha
Classifier: Operating System :: OS Independent
Classifier: Programming Language :: Python :: 3.5
Classifier: Topic :: Software Development :: Libraries :: Python Modules
